mlutils/__init__.py
mlutils/torchtools/__init__.py
mlutils/torchtools/helpers.py
mlutils/torchtools/metrics.py
ml_dev_tools-0.0.2.dist-info/LICENSE
ml_dev_tools-0.0.2.dist-info/METADATA
ml_dev_tools-0.0.2.dist-info/WHEEL
ml_dev_tools-0.0.2.dist-info/top_level.txt
ml_dev_tools-0.0.2.dist-info/RECORD
